socrates_api/__init__.py
socrates_api/auth.py
socrates_api/ipam.py
socrates_api/models.py
socrates_api/serializers.py
socrates_api/tasks.py
socrates_api/tests.py
socrates_api/urls.py
socrates_api/views.py
socrates_api/migrations/0001_initial.py
socrates_api/migrations/0002_auto_20170120_0949.py
socrates_api/migrations/__init__.py
socrates_api/templates/end-of-life.mail.j2
socrates_api/templates/expiring-warranty.mail.j2
socrates_api/templates/libvirt-attach-interface.xml
socrates_api/templates/libvirt-attach-volume.xml
socrates_api/templates/libvirt-create-bridge-interface.xml
socrates_api/templates/libvirt-create-network.xml
socrates_api/templates/libvirt-create-volume.xml
socrates_api/templates/no-warranty.mail.j2
socrates_api/templatetags/__init__.py
socrates_api/templatetags/kickstart.py
socrates_api/templatetags/libvirt.py
socrates_api-2.0.12.dist-info/AUTHORS.txt
socrates_api-2.0.12.dist-info/LICENSE.txt
socrates_api-2.0.12.dist-info/METADATA
socrates_api-2.0.12.dist-info/WHEEL
socrates_api-2.0.12.dist-info/top_level.txt
socrates_api-2.0.12.dist-info/RECORD
