Metadata-Version: 2.1
Name: socrates-api
Version: 2.0.12
Summary: Source of Truth for hardware, virtual machines, and networks
Home-page: https://github.com/dhozac/socrates_api
Author: Klarna Bank AB
Author-email: daniel.zakrisson@klarna.com
License: Apache Software License
Platform: UNKNOWN
Classifier: Development Status :: 7 - Inactive
Classifier: Environment :: Web Environment
Classifier: Framework :: Django :: 1.11
Classifier: Intended Audience :: System Administrators
Classifier: License :: OSI Approved :: Apache Software License
Classifier: Topic :: System :: Installation/Setup
Requires-Dist: Django
Requires-Dist: rethinkdb
Requires-Dist: celery
Requires-Dist: djangorestframework
Requires-Dist: gevent (>1.0.0)
Requires-Dist: requests
Requires-Dist: jsonpath-rw-ext
Requires-Dist: netaddr
Requires-Dist: deepdiff (>3.2.0)
Requires-Dist: django-rethink (>0.5.2)
